ggs.py
ggs-0.1.dist-info/LICENSE
ggs-0.1.dist-info/METADATA
ggs-0.1.dist-info/WHEEL
ggs-0.1.dist-info/top_level.txt
ggs-0.1.dist-info/RECORD
