Metadata-Version: 2.1
Name: ggs
Version: 0.1
Summary: Greedy grid search for hyper-parameter optimization.
Home-page: https://github.com/enzobusseti/greedy_grid_search
Author: Enzo Busseti
Author-email: enzo.busseti@gmail.com
License: GPLv3
Platform: UNKNOWN
